compare_variance_residual/__init__.py
compare_variance_residual/fmri_comparison/__init__.py
compare_variance_residual/fmri_comparison/extract_context_representations.py
compare_variance_residual/fmri_comparison/joint_prediction.py
compare_variance_residual/fmri_comparison/low_level_prediction.py
compare_variance_residual/fmri_comparison/residual_prediction.py
compare_variance_residual/fmri_comparison/semantic_prediction.py
compare_variance_residual/fmri_comparison/variance_partitioning.py
compare_variance_residual/simulated/__init__.py
compare_variance_residual/simulated/plotting.py
compare_variance_residual/simulated/residual.py
compare_variance_residual/simulated/simulation.py
compare_variance_residual/simulated/stacked_regression.py
compare_variance_residual/simulated/variance_partitioning.py
compare_variance_residual-0.0.3.dist-info/LICENSE
compare_variance_residual-0.0.3.dist-info/METADATA
compare_variance_residual-0.0.3.dist-info/WHEEL
compare_variance_residual-0.0.3.dist-info/top_level.txt
compare_variance_residual-0.0.3.dist-info/RECORD
