Metadata-Version: 2.2
Name: compare_variance_residual
Version: 0.0.3
Summary: Code for the bachelor thesis of Leo Schultheiss
Author-email: Leo Schultheiss <leo.schultheiss@tum.de>
License: Copyright (c) 2018 The Python Packaging Authority
Project-URL: Homepage, https://github.com/leo-schultheiss/compare_variance_residual/tree/master
Project-URL: Issues, https://github.com/leo-schultheiss/compare_variance_residual/issues
Keywords: fMRI,neuroimaging,statistics,variance partitioning
Classifier: Programming Language :: Python :: 3
Classifier: Operating System :: POSIX :: Linux
Requires-Python: >=3.8
License-File: LICENSE
Requires-Dist: requests>=2.32.3
Requires-Dist: tqdm>=4.66.5
Requires-Dist: transformers>=4.45.2
Requires-Dist: torch>=2.5.0
Requires-Dist: pandas>=2.2.3
Requires-Dist: numpy>=2.1.2
Requires-Dist: tables>=3.10.1
Requires-Dist: scipy>=1.14.1
Requires-Dist: h5py>=3.12.1
Requires-Dist: ridge-utils>=0.2.0
Requires-Dist: gitpython>=3.1.43
Requires-Dist: himalaya>=0.4.6
Requires-Dist: scikit-learn>=1.5.2
Requires-Dist: matplotlib>=3.9.2
Requires-Dist: voxelwise-tutorials>=0.1.7
Requires-Dist: stacking-fmri>=0.1.1
